pypamguard/__init__.py
pypamguard/_version.py
pypamguard/documentation.md
pypamguard/load_pamguard_binary_file.py
pypamguard/load_pamguard_binary_folder.py
pypamguard/load_pamguard_multi_file.py
pypamguard/logger.py
pypamguard/main.py
pypamguard/chunks/annotations/__init__.py
pypamguard/chunks/annotations/annotationmanager.py
pypamguard/chunks/annotations/baseannotation.py
pypamguard/chunks/annotations/beamformer.py
pypamguard/chunks/annotations/bearing.py
pypamguard/chunks/annotations/clickclsfr.py
pypamguard/chunks/annotations/dl.py
pypamguard/chunks/annotations/matchcls.py
pypamguard/chunks/annotations/rwudp.py
pypamguard/chunks/annotations/tbdl.py
pypamguard/chunks/annotations/tm.py
pypamguard/chunks/annotations/userform.py
pypamguard/chunks/annotations/submodules/__init__.py
pypamguard/chunks/annotations/submodules/location.py
pypamguard/chunks/annotations/submodules/modeldata.py
pypamguard/chunks/base/__init__.py
pypamguard/chunks/base/chunk.py
pypamguard/chunks/generics/__init__.py
pypamguard/chunks/generics/genbackground.py
pypamguard/chunks/generics/genchunkinfo.py
pypamguard/chunks/generics/genfilefooter.py
pypamguard/chunks/generics/genfileheader.py
pypamguard/chunks/generics/genmodule.py
pypamguard/chunks/generics/genmodulefooter.py
pypamguard/chunks/generics/genmoduleheader.py
pypamguard/chunks/modules/__init__.py
pypamguard/chunks/modules/classifiers/deeplearningclassifier.py
pypamguard/chunks/modules/detectors/click.py
pypamguard/chunks/modules/detectors/clicktriggerbackground.py
pypamguard/chunks/modules/detectors/gpl.py
pypamguard/chunks/modules/detectors/rwedge.py
pypamguard/chunks/modules/detectors/spectralbackground.py
pypamguard/chunks/modules/detectors/whistleandmoan.py
pypamguard/chunks/modules/plugins/geminithreshold.py
pypamguard/chunks/modules/plugins/spermwhaleipi.py
pypamguard/chunks/modules/processing/ais.py
pypamguard/chunks/modules/processing/clipgenerator.py
pypamguard/chunks/modules/processing/dbht.py
pypamguard-1.0.1.dist-info/METADATA
pypamguard-1.0.1.dist-info/WHEEL
pypamguard-1.0.1.dist-info/licenses/LICENSE
pypamguard-1.0.1.dist-info/RECORD
