Metadata-Version: 2.4
Name: pypamguard
Version: 1.0.1
Summary: A package for processing PAMGuard binary file outputs in Python.
Author-email: James Sullivan <pamguard@st-andrews.ac.uk>
License-Expression: MIT
License-File: LICENSE
Classifier: Operating System :: OS Independent
Classifier: Programming Language :: Python :: 3 :: Only
Requires-Python: >3.9
Requires-Dist: numpy
